<persistence xmlns="http://xmlns.jcp.org/xml/ns/persistence"
  xmlns:xsi="http://www.w3.org/2001/XMLSchema-instance"
  xsi:schemaLocation="http://xmlns.jcp.org/xml/ns/persistence
  http://xmlns.jcp.org/xml/ns/persistence/persistence_2_1.xsd"
  version="2.1">
  <persistence-unit name="jbd-pu">
    <provider>org.hibernate.jpa.HibernatePersistenceProvider</provider>
    <properties>
      <property name="javax.persistence.jdbc.driver" value="org.postgresql.Driver" />
      <property name="javax.persistence.jdbc.url"
        value="jdbc:postgresql://rjawntleivocyn:9f83f6f88a836ff4a0a25cb355163245afe8930f01e642db77580cfbfe6a5341@ec2-176-34-234-47.eu-west-1.compute.amazonaws.com:5432/d7e1gv3evoq8h8?sslmode=require" />
      <property name="javax.persistence.jdbc.user" value="postgres" />
      <property name="javax.persistence.jdbc.password"
        value="Stas2002" />
      <property name="hibernate.show_sql" value="true" />
      <property name="hibernate.dialect"
        value="org.hibernate.dialect.PostgreSQLDialect" />
    </properties>
  </persistence-unit>
</persistence>